Metadata-Version: 2.4
Name: django-chatkit
Version: 0.1.1
Summary: A pluggable real-time chat app for Django (Channels) with multi-file uploads and light/dark UI.
Author-email: kawsar alam foysal <kawsaralam.ofc@gmail.com>
License-Expression: BSD-3-Clause
Project-URL: Homepage, https://github.com/iamfoysal/django-chatkit
Project-URL: Repository, https://github.com/iamfoysal/django-chatkit
Project-URL: Issues, https://github.com/iamfoysal/django-chatkit/issues
Keywords: django,chat,websocket,channels,real-time
Classifier: Framework :: Django
Classifier: Framework :: Django :: 4.2
Classifier: Programming Language :: Python :: 3
Classifier: Programming Language :: Python :: 3.10
Classifier: Programming Language :: Python :: 3.11
Classifier: Programming Language :: Python :: 3.12
Classifier: Intended Audience :: Developers
Classifier: Operating System :: OS Independent
Requires-Python: >=3.10
License-File: LICENSE
Requires-Dist: Django>=4.2
Requires-Dist: channels>=4.1
Requires-Dist: daphne>=4.0
Requires-Dist: whitenoise>=6.0
Requires-Dist: Pillow>=10.0.0
Requires-Dist: channels-redis>=4.0
Dynamic: license-file
